datist/VERSION
datist/__init__.py
datist/main.py
datist-0.1.0.dist-info/DESCRIPTION.rst
datist-0.1.0.dist-info/METADATA
datist-0.1.0.dist-info/RECORD
datist-0.1.0.dist-info/WHEEL
datist-0.1.0.dist-info/metadata.json
datist-0.1.0.dist-info/top_level.txt
